crawler/__init__.py
crawler/crawler.py
SteamUserFind-0.1.dist-info/METADATA
SteamUserFind-0.1.dist-info/WHEEL
SteamUserFind-0.1.dist-info/top_level.txt
SteamUserFind-0.1.dist-info/RECORD
